flask_app_aly_cis/__init__.py
flask_app_aly_cis/__main__.py
flask_app_aly_cis/apis/__init__.py
flask_app_aly_cis/apis/v1/__init__.py
flask_app_aly_cis/apis/v1/health.py
flask_app_aly_cis/core/__init__.py
flask_app_aly_cis/core/exception.py
flask_app_aly_cis/core/exception_handler.py
flask_app_aly_cis/encoder.py
flask_app_aly_cis/settings.py
flask_app_aly_cis/swagger/swagger.yaml
flask_app_aly_cis-0.0.0.dist-info/LICENSE
flask_app_aly_cis-0.0.0.dist-info/METADATA
flask_app_aly_cis-0.0.0.dist-info/WHEEL
flask_app_aly_cis-0.0.0.dist-info/RECORD
