Metadata-Version: 2.1
Name: flask_app_aly_cis
Version: 0.0.0
Summary: 
License: MIT
Author: CISSE ALY
Author-email: alyhabcis@gmail.com
Requires-Python: ==3.10.12
Classifier: License :: OSI Approved :: MIT License
Classifier: Programming Language :: Python :: 3
Requires-Dist: Flask (==2.2.2)
Requires-Dist: Flask-Caching (==2.0.2)
Requires-Dist: connexion[swagger-ui] (>=2.14.2,<3.0.0)
Requires-Dist: cryptography (>=39.0.1,<40.0.0)
Requires-Dist: flask-alembic (>=2.0.1,<3.0.0)
Requires-Dist: flask-cors (>=3.0.10,<4.0.0)
Requires-Dist: flask-migrate (>=4.0.4,<5.0.0)
Requires-Dist: flask-request-id-header (>=0.1.1,<0.2.0)
Requires-Dist: flask-sqlalchemy (>=3.0.3,<4.0.0)
Requires-Dist: gunicorn (>=20.1.0,<21.0.0)
Requires-Dist: prometheus-flask-exporter (>=0.22.3,<0.23.0)
Requires-Dist: tenacity (>=8.2.3,<9.0.0)
Requires-Dist: wheel (>=0.43.0,<0.44.0)
